apilage/__init__.py
apilage/interpreter.py
apilage-1.0.1.dist-info/METADATA
apilage-1.0.1.dist-info/WHEEL
apilage-1.0.1.dist-info/entry_points.txt
apilage-1.0.1.dist-info/top_level.txt
apilage-1.0.1.dist-info/RECORD
