Metadata-Version: 2.1
Name: apilage
Version: 1.0.1
Summary: A beginner-friendly programming language.
Home-page: https://github.com/yourusername/apilage
Author: Pasindu Dewviman
Author-email: your-email@example.com
Classifier: Programming Language :: Python
Classifier: License :: OSI Approved :: MIT License
Classifier: Operating System :: OS Independent
Requires-Python: >=3.6
